aiaf/__init__.py
aiaf/aiaf.py
aiaf-0.3.0.dist-info/METADATA
aiaf-0.3.0.dist-info/WHEEL
aiaf-0.3.0.dist-info/top_level.txt
aiaf-0.3.0.dist-info/RECORD
