Metadata-Version: 2.4
Name: aiaf
Version: 0.3.0
Summary: AI Agent Firewall: Prevents prompt injection and adversarial attacks on AI chatbots.
Home-page: https://github.com/Nathan8044/aiaf
Author: Your Name
Author-email: nathanrampersaud@gmail.com
License: MIT
Classifier: Programming Language :: Python :: 3
Classifier: License :: OSI Approved :: MIT License
Classifier: Operating System :: OS Independent
Requires-Python: >=3.7
Requires-Dist: openai
Dynamic: author
Dynamic: author-email
Dynamic: classifier
Dynamic: home-page
Dynamic: requires-dist
Dynamic: requires-python
Dynamic: summary
